{"is_source_file": true, "format": "bash", "description": "This is a shell script that automates restoring various types of databases (SQLite, PostgreSQL, MySQL, MongoDB) from backup files. It detects existing backup files and service statuses, then executes corresponding restore commands.", "external_files": ["database_backup.db", "database_backup.sql", "database_backup.archive"], "external_methods": ["pg_isready", "psql", "mysqladmin", "mysql", "mongosh", "mongorestore"], "published": [], "classes": [], "methods": [], "calls": ["ls", "sudo -u postgres pg_isready", "psql", "mysqladmin ping", "mysql", "mongosh", "mongorestore", "echo", "exit"], "search-terms": ["restore_db.sh", "database restore script", "PostgreSQL restore", "MySQL restore", "MongoDB restore", "backup detection", "database restore script", "shell restore script"], "state": 2, "file_id": 8, "knowledge_revision": 14, "git_revision": "fdf2522b590d6a7ca4778bb5d6252c28683b7e40", "hash": "d42c3e6cbc3bbd627e3c08afcf4183ec", "format-version": 4, "code-base-name": "postgresql_database", "filename": "postgresql_database/restore_db.sh", "revision_history": [{"14": "fdf2522b590d6a7ca4778bb5d6252c28683b7e40"}]}